spaste/__init__.py
spaste-0.0.3.dist-info/METADATA
spaste-0.0.3.dist-info/WHEEL
spaste-0.0.3.dist-info/entry_points.txt
spaste-0.0.3.dist-info/top_level.txt
spaste-0.0.3.dist-info/RECORD
