Metadata-Version: 2.1
Name: spaste
Version: 0.0.3
Summary: The official client for spaste.io
Home-page: https://spaste.io
Author: spaste
Author-email: hello@spaste.io
License: UNKNOWN
Keywords: shell
Platform: UNKNOWN
Classifier: Development Status :: 3 - Alpha
Classifier: Intended Audience :: Developers
Classifier: Topic :: Software Development :: Version Control
Classifier: Programming Language :: Python :: 3
Classifier: Programming Language :: Python :: 3.2
Classifier: Programming Language :: Python :: 3.3
Classifier: Programming Language :: Python :: 3.4
Classifier: Programming Language :: Python :: 3.5
Classifier: Programming Language :: Python :: 3.6
Requires-Dist: asyncio
Requires-Dist: colorful
Requires-Dist: websockets
